nekosbest/__init__.py
nekosbest/client.py
nekosbest/errors.py
nekosbest/http.py
nekosbest/models.py
nekosbest/types.py
nekosbest-1.1.14.dist-info/licenses/LICENSE
nekosbest-1.1.14.dist-info/METADATA
nekosbest-1.1.14.dist-info/WHEEL
nekosbest-1.1.14.dist-info/top_level.txt
nekosbest-1.1.14.dist-info/RECORD
