Metadata-Version: 2.4
Name: nekosbest
Version: 1.1.14
Summary: A simple async Python wrapper for nekos.best API.
Home-page: https://github.com/nekos-best/nekos-best.py
Author: PredaaA (preda__)
License: AGPLv3
Project-URL: Issue Tracker, https://github.com/nekos-best/nekos-best.py/issues
Project-URL: Source Code, https://github.com/nekos-best/nekos-best.py
Classifier: Development Status :: 5 - Production/Stable
Classifier: Framework :: AsyncIO
Classifier: Intended Audience :: Developers
Classifier: License :: OSI Approved :: GNU Affero General Public License v3 or later (AGPLv3+)
Classifier: Natural Language :: English
Classifier: Operating System :: OS Independent
Classifier: Programming Language :: Python :: 3.9
Classifier: Programming Language :: Python :: 3.10
Classifier: Programming Language :: Python :: 3.11
Classifier: Programming Language :: Python :: 3.12
Classifier: Programming Language :: Python :: 3.13
Classifier: Topic :: Internet
Classifier: Topic :: Software Development :: Libraries
Classifier: Topic :: Software Development :: Libraries :: Python Modules
Classifier: Topic :: Utilities
Requires-Python: >=3.8.0
License-File: LICENSE
Requires-Dist: aiohttp<4,>=3.7.4
Dynamic: license-file
